camera_geometry/__init__.py
camera_geometry/cam_model.py
sampler/__init__.py
sampler/gui.py
camera_geometry-0.0.5.dist-info/METADATA
camera_geometry-0.0.5.dist-info/WHEEL
camera_geometry-0.0.5.dist-info/entry_points.txt
camera_geometry-0.0.5.dist-info/top_level.txt
camera_geometry-0.0.5.dist-info/RECORD
