Metadata-Version: 2.4
Name: camera-geometry
Version: 0.0.5
Summary: Camera geometry utilities: sampling GUI and pixel->elevation model
Author-email: Eliot Janvier <eliot.janvier@gmail.com>
Requires-Python: >=3.10
Requires-Dist: numpy>=1.21
Provides-Extra: sampler
Requires-Dist: opencv-python>=4.5; extra == "sampler"
Requires-Dist: Pillow>=8.0; extra == "sampler"
Requires-Dist: matplotlib>=3.0; extra == "sampler"
